<videos>
  <item n="0">
    <title>Nas-Belly Button Window</title>
    <vidurl><![CDATA[http://www.youtube.com/v/deteOPL6J_Y?f=videos&app=youtube_gdata]]></vidurl>
  </item>
  <item n="1">
    <title>Kashmere - Opium Foetus VS. NaS - Fetus (Belly Button Window)</title>
    <vidurl><![CDATA[http://www.youtube.com/v/U3Ida20zi-Y?f=videos&app=youtube_gdata]]></vidurl>
  </item>
  <item n="2">
    <title>Large Professor Nas-One Plus One</title>
    <vidurl><![CDATA[http://www.youtube.com/v/EbXhMRFGoks?f=videos&app=youtube_gdata]]></vidurl>
  </item>
  <item n="3">
    <title>Nas - The Lost Tapes (Underrated Classic)</title>
    <vidurl><![CDATA[http://www.youtube.com/v/C9kaX16BNlo?f=videos&app=youtube_gdata]]></vidurl>
  </item>
  <item n="4">
    <title>nas-fetus</title>
    <vidurl><![CDATA[http://www.youtube.com/v/Cjuogayzm5U?f=videos&app=youtube_gdata]]></vidurl>
  </item>
  <item n="5">
    <title>NAS Pensacola, FL: Blue Angels Practice</title>
    <vidurl><![CDATA[http://www.youtube.com/v/9_pAjbs0z6o?f=videos&app=youtube_gdata]]></vidurl>
  </item>
  <item n="6">
    <title>Keyshia Cole Ft Nas Oh Oh, Yeah, Yeah</title>
    <vidurl><![CDATA[http://www.youtube.com/v/KKFdIANfo6Q?f=videos&app=youtube_gdata]]></vidurl>
  </item>
  <item n="7">
    <title>ClutchBoy - You (Produced By NmCmal) [LYRICS + DOWNLOAD LINK] (Original Track)</title>
    <vidurl><![CDATA[http://www.youtube.com/v/oE0jVHQHHS0?f=videos&app=youtube_gdata]]></vidurl>
  </item>
  <item n="8">
    <title>Dua Qunoot - Namaz - Witr - (With English Translation)</title>
    <vidurl><![CDATA[http://www.youtube.com/v/NJ4vbqS44cM?f=videos&app=youtube_gdata]]></vidurl>
  </item>
  <item n="9">
    <title>Pokémon - FireRed - How to find Lugia? / Jak znaleźć(złapać) Lugię?</title>
    <vidurl><![CDATA[http://www.youtube.com/v/p5O5_4jpweY?f=videos&app=youtube_gdata]]></vidurl>
  </item>
  <item n="10">
    <title>William James  (W6MUV).  Memorial</title>
    <vidurl><![CDATA[rtsp://v3.cache5.c.youtube.com/CiILENy73wIaGQk_9IEBtJixARMYDSANFEgGUgZ2aWRlb3MM/0/0/0/video.3gp]]></vidurl>
  </item>
  <item n="11">
    <title>Boca Chica Airbase Key West lobster 2 FILE0002 32</title>
    <vidurl><![CDATA[http://www.youtube.com/v/wYGSF7nkuds?f=videos&app=youtube_gdata]]></vidurl>
  </item>
  <item n="12">
    <title>Like This - 4Bidin and The Protege [[Download Link Included]]</title>
    <vidurl><![CDATA[http://www.youtube.com/v/nd83_ipR5jY?f=videos&app=youtube_gdata]]></vidurl>
  </item>
</videos>